[
  {
    "id":101,
    "name":"Gunung Tahan",
    "latitude": 4.633008,
    "longitude": 102.234970,
    "state": "Pahang",
    "distance":"Feet:7175/Meter: 2187"
  },
  {
    "id":102,
    "name":"Gunung Korbu",
    "latitude": 4.683333,
    "longitude": 101.300003,
    "state": "Perak",
    "distance":"Feet:7162/Meter:2183"
  },
  {
    "id":103,
    "name":"Gunung Yong Belar",
    "latitude": 4.650000,
    "longitude": 101.361664,
    "state": "Perak",
    "distance":"Feet:7156/Meter:2181"
  },
  {
    "id":104,
    "name":"Gunung Gayong",
    "latitude": 4.683333,
    "longitude": 101.316666,
    "state": "Perak",
    "distance":"Feet:7129/Meter:2173"
  },
  {
    "id":105,
    "name":"Gunung Chamah",
    "latitude": 5.216667,
    "longitude": 101.583336,
    "state": "Kelantan",
    "distance":"Feet:7123/Meter:2171"
  },
  {
    "id":106,
    "name":"Gunung Yong Yap",
    "latitude": 4.750000,
    "longitude": 101.383331,
    "state": "Kelantan",
    "distance":"Feet:7113/Meter:2167"
  },
  {
    "id":107,
    "name":"Gunung Ulu Sepat",
    "latitude": 5.150000,
    "longitude": 101.483330,
    "state": "Kelantan",
    "distance":"Feet:7090/Meter: 2161"
  }
]